dynamodb_mapping/__init__.py
dynamodb_mapping/dynamodb_mapping.py
dynamodb_mapping/py.typed
dynamodb_mapping-0.1.1.dist-info/AUTHORS.rst
dynamodb_mapping-0.1.1.dist-info/LICENSE
dynamodb_mapping-0.1.1.dist-info/METADATA
dynamodb_mapping-0.1.1.dist-info/WHEEL
dynamodb_mapping-0.1.1.dist-info/top_level.txt
dynamodb_mapping-0.1.1.dist-info/RECORD
