Metadata-Version: 2.1
Name: dynamodb-mapping
Version: 0.1.1
Summary: A Python dictionary-like interface for an Amazon DynamoDB table.
Home-page: https://github.com/mrtj/dynamodb_mapping
Author: Janos Tolgyesi
Author-email: janos.tolgyesi@gmail.com
License: MIT license
Keywords: dynamodb_mapping
Classifier: Development Status :: 2 - Pre-Alpha
Classifier: Intended Audience :: Developers
Classifier: License :: OSI Approved :: MIT License
Classifier: Natural Language :: English
Classifier: Programming Language :: Python :: 3
Classifier: Programming Language :: Python :: 3.8
Classifier: Programming Language :: Python :: 3.9
Classifier: Programming Language :: Python :: 3.10
Requires-Python: >=3.8
License-File: LICENSE
License-File: AUTHORS.rst
Requires-Dist: boto3
